napari_nyxus/__init__.py
napari_nyxus/_version.py
napari_nyxus/napari.yaml
napari_nyxus/nyx.py
napari_nyxus/nyx_napari.py
napari_nyxus/util/__init__.py
napari_nyxus/util/rotated_header.py
napari_nyxus/util/util.py
napari_nyxus-0.2.1.dist-info/LICENSE
napari_nyxus-0.2.1.dist-info/METADATA
napari_nyxus-0.2.1.dist-info/WHEEL
napari_nyxus-0.2.1.dist-info/entry_points.txt
napari_nyxus-0.2.1.dist-info/top_level.txt
napari_nyxus-0.2.1.dist-info/RECORD
