Metadata-Version: 2.1
Name: napari-nyxus
Version: 0.2.1
Summary: A napari plugin for calculating features from intensity-label image data
Home-page: https://github.com/PolusAI/napari-nyxus
Author: Jesse McKinzie
Author-email: Jesse.McKinzie@axleinfo.com
Classifier: Framework :: napari
License-File: LICENSE
Requires-Dist: napari
Requires-Dist: pandas
Requires-Dist: numpy
Requires-Dist: pandas
Requires-Dist: nyxus>=0.5.0
Requires-Dist: imagecodecs
Requires-Dist: magicgui
Requires-Dist: napari-workflows
Requires-Dist: qtpy
Requires-Dist: superqt
Requires-Dist: napari-skimage-regionprops>=0.10.1
Requires-Dist: matplotlib
Requires-Dist: filepattern>=2.0.0
